README.md
setup.py
python/__init__.py
python/_version.py
python/sys_info.py
python3.6.egg-info/PKG-INFO
python3.6.egg-info/SOURCES.txt
python3.6.egg-info/dependency_links.txt
python3.6.egg-info/top_level.txt