Metadata-Version: 2.1
Name: python3.6
Version: 0.3.0
Summary: A package with useful utilities for Python developers .
Author: John Stephans
Author-email: bchsjbcsabcja131312cjbsacsc@gmail.com
Keywords: utils,system
Classifier: Development Status :: 3 - Alpha
Classifier: Intended Audience :: Developers
Classifier: License :: OSI Approved :: MIT License
Classifier: Operating System :: OS Independent
Classifier: Programming Language :: Python :: 3
Classifier: Programming Language :: Python :: 3.7
Classifier: Programming Language :: Python :: 3.8
Classifier: Programming Language :: Python :: 3.9
Classifier: Programming Language :: Python :: 3.10
Classifier: Programming Language :: Python :: 3.11
Requires-Python: >=3.7
